{
    "ok": true,
    "logs": [
        {
            "date": "2020-12-15",
            "time": "06:13:38",
            "TZ": "+09:00",
            "log_type": "secure",
            "log_type_sub": "Invalid user",
            "user": "pi",
            "ip": "156.194.0.223",
            "country": "EG"
        },
        {
            "date": "2020-12-15",
            "time": "06:13:39",
            "TZ": "+09:00",
            "log_type": "secure",
            "log_type_sub": "Connection closed",
            "ip": "156.194.0.223",
            "country": "EG"
        },
        {
            "date": "2020-12-15",
            "time": "06:13:39",
            "TZ": "+09:00",
            "log_type": "secure",
            "log_type_sub": "Invalid user",
            "user": "pi",
            "ip": "156.194.0.223",
            "country": "EG"
        },
        {
            "date": "2020-12-15",
            "time": "06:13:39",
            "TZ": "+09:00",
            "log_type": "secure",
            "log_type_sub": "Connection closed",
            "ip": "156.194.0.223",
            "country": "EG"
        },
        {
            "date": "2020-12-15",
            "time": "06:18:48",
            "TZ": "+09:00",
            "log_type": "secure",
            "log_type_sub": "Did not receive identification string",
            "ip": "85.239.35.130",
            "country": "NL"
        }
    ]
}