{
    "ok": true,
    "logs": [
        {
            "date": "2020-12-13",
            "time": "01:45:07",
            "TZ": "+09:00",
            "log_type": "secure",
            "log_type_sub": "Invalid user",
            "user": "fal",
            "ip": "106.55.236.107",
            "country": "CN"
        },
        {
            "date": "2020-12-13",
            "time": "01:46:39",
            "TZ": "+09:00",
            "log_type": "secure",
            "log_type_sub": "Invalid user",
            "user": "user",
            "ip": "134.209.241.227",
            "country": "US"
        },
        {
            "date": "2020-12-13",
            "time": "01:47:39",
            "TZ": "+09:00",
            "log_type": "secure",
            "log_type_sub": "Invalid user",
            "user": "ik",
            "ip": "202.137.10.182",
            "country": "ID"
        },
        {
            "date": "2020-12-13",
            "time": "01:53:29",
            "TZ": "+09:00",
            "log_type": "secure",
            "log_type_sub": "Invalid user",
            "user": "developer",
            "ip": "101.231.146.34",
            "country": "CN"
        }
    ]
}