{
    "ok": true,
    "logs": [
        {
            "date": "2020-06-29",
            "time": "23:49:24",
            "TZ": "+09:00",
            "log_type": "secure",
            "log_type_sub": "Invalid user",
            "user": "zxc",
            "ip": "139.155.90.141",
            "country": "CN"
        },
        {
            "date": "2020-06-29",
            "time": "23:49:58",
            "TZ": "+09:00",
            "log_type": "secure",
            "log_type_sub": "Did not receive identification string",
            "ip": "85.209.0.102",
            "country": "NL"
        },
        {
            "date": "2020-06-29",
            "time": "23:52:37",
            "TZ": "+09:00",
            "log_type": "secure",
            "log_type_sub": "Invalid user",
            "user": "postgres",
            "ip": "212.95.137.164",
            "country": "US"
        },
        {
            "date": "2020-06-29",
            "time": "23:53:50",
            "TZ": "+09:00",
            "log_type": "secure",
            "log_type_sub": "Did not receive identification string",
            "ip": "61.19.54.165",
            "country": "TH"
        }
    ]
}