{
    "ok": true,
    "logs": [
        {
            "date": "2020-11-02",
            "time": "22:15:25",
            "TZ": "+09:00",
            "log_type": "secure",
            "log_type_sub": "Did not receive identification string",
            "ip": "85.209.0.253",
            "country": "NL"
        },
        {
            "date": "2020-11-02",
            "time": "22:15:34",
            "TZ": "+09:00",
            "log_type": "secure",
            "log_type_sub": "Connection closed",
            "ip": "85.209.0.253",
            "country": "NL"
        },
        {
            "date": "2020-11-02",
            "time": "22:15:34",
            "TZ": "+09:00",
            "log_type": "secure",
            "log_type_sub": "Connection closed",
            "ip": "85.209.0.253",
            "country": "NL"
        },
        {
            "date": "2020-11-02",
            "time": "22:16:51",
            "TZ": "+09:00",
            "log_type": "secure",
            "log_type_sub": "Connection closed",
            "ip": "75.165.117.55",
            "country": "US"
        },
        {
            "date": "2020-11-02",
            "time": "22:40:57",
            "TZ": "+09:00",
            "log_type": "secure",
            "log_type_sub": "Did not receive identification string",
            "ip": "139.162.247.102",
            "country": "US"
        },
        {
            "date": "2020-11-02",
            "time": "22:43:02",
            "TZ": "+09:00",
            "log_type": "secure",
            "log_type_sub": "Invalid user",
            "user": "nexus",
            "ip": "183.82.121.34",
            "country": "IN"
        },
        {
            "date": "2020-11-02",
            "time": "22:45:04",
            "TZ": "+09:00",
            "log_type": "secure",
            "log_type_sub": "Connection closed",
            "ip": "139.162.247.102",
            "country": "US"
        },
        {
            "date": "2020-11-02",
            "time": "22:45:06",
            "TZ": "+09:00",
            "log_type": "secure",
            "log_type_sub": "Connection closed",
            "ip": "139.162.247.102",
            "country": "US"
        },
        {
            "date": "2020-11-02",
            "time": "22:45:09",
            "TZ": "+09:00",
            "log_type": "secure",
            "log_type_sub": "Connection closed",
            "ip": "139.162.247.102",
            "country": "US"
        }
    ]
}